example/manage.py
example/example/__init__.py
example/example/settings.py
example/example/urls.py
example/example/wsgi.py
example/example/app/__init__.py
example/example/app/admin.py
example/example/app/models.py
example/example/app/tests.py
example/example/app/urls.py
example/example/app/views.py
example/example/app/migrations/0001_initial.py
example/example/app/migrations/__init__.py
radiogrid/__init__.py
radiogrid/compat.py
radiogrid/db.py
radiogrid/fields.py
radiogrid/widgets.py
radiogrid/templates/radiogrid/radiogrid_input.html
radiogrid/templates/radiogrid/radiogrid_widget.html
django_radiogrid-1.1.0.dist-info/COPYING.LGPLv3
django_radiogrid-1.1.0.dist-info/METADATA
django_radiogrid-1.1.0.dist-info/WHEEL
django_radiogrid-1.1.0.dist-info/top_level.txt
django_radiogrid-1.1.0.dist-info/RECORD
