Metadata-Version: 2.1
Name: django-radiogrid
Version: 1.1.0
Summary: Django radio grid field
Home-page: https://github.com/Sinkler/django-radiogrid
Author: Anton Shurashov
Author-email: sinkler@sinkler.ru
License: LGPL 3
Keywords: django,radio,grid,field,choices
Classifier: Development Status :: 5 - Production/Stable
Classifier: Framework :: Django
Classifier: License :: OSI Approved :: GNU Library or Lesser General Public License (LGPL)
Classifier: Programming Language :: Python :: 2
Classifier: Programming Language :: Python :: 3
License-File: COPYING.LGPLv3
